{
  "insert-template": [
    {
      "modifiers": [
        "Alt"
      ],
      "key": "T"
    }
  ],
  "omnisearch:show-modal": [
    {
      "modifiers": [
        "Mod"
      ],
      "key": "O"
    }
  ],
  "switcher:open": [],
  "app:go-back": [
    {
      "modifiers": [
        "Alt",
        "Mod"
      ],
      "key": "H"
    }
  ],
  "obsidian-admonition:insert-admonition": [
    {
      "modifiers": [
        "Alt",
        "Mod"
      ],
      "key": "P"
    }
  ],
  "workspace:close-others": [
    {
      "modifiers": [
        "Mod",
        "Shift"
      ],
      "key": "Q"
    }
  ],
  "app:delete-file": [
    {
      "modifiers": [
        "Mod"
      ],
      "key": "Delete"
    }
  ],
  "editor:toggle-checklist-status": [],
  "editor:focus-left": [
    {
      "modifiers": [
        "Mod",
        "Shift"
      ],
      "key": "H"
    }
  ],
  "editor:focus-right": [
    {
      "modifiers": [
        "Mod",
        "Shift"
      ],
      "key": "L"
    }
  ],
  "app:go-forward": [
    {
      "modifiers": [
        "Alt",
        "Mod"
      ],
      "key": "L"
    }
  ],
  "editor:insert-mathblock": [
    {
      "modifiers": [
        "Alt"
      ],
      "key": "M"
    }
  ],
  "workspace:open-in-new-window": [
    {
      "modifiers": [
        "Alt",
        "Mod"
      ],
      "key": "W"
    }
  ],
  "workspace:edit-file-title": [
    {
      "modifiers": [
        "Alt",
        "Mod"
      ],
      "key": "R"
    }
  ],
  "editor:swap-line-down": [
    {
      "modifiers": [
        "Alt",
        "Mod"
      ],
      "key": "J"
    }
  ],
  "editor:swap-line-up": [
    {
      "modifiers": [
        "Alt",
        "Mod"
      ],
      "key": "K"
    }
  ],
  "file-explorer:new-file-in-new-pane": []
}