{
  "main": {
    "id": "39c86b6d219e1472",
    "type": "split",
    "children": [
      {
        "id": "431f32472dabe4ca",
        "type": "tabs",
        "children": [
          {
            "id": "d658c1672502be5c",
            "type": "leaf",
            "state": {
              "type": "markdown",
              "state": {
                "file": "2o Mates/201 Topología/Subespacios topológicos.md",
                "mode": "source",
                "backlinks": false,
                "source": false
              },
              "icon": "lucide-file",
              "title": "Subespacios topológicos"
            }
          },
          {
            "id": "af4156d29bcf8da3",
            "type": "leaf",
            "state": {
              "type": "markdown",
              "state": {
                "file": "2o Mates/201 Topología/Subespacios topológicos.md",
                "mode": "source",
                "backlinks": false,
                "source": false
              },
              "icon": "lucide-file",
              "title": "Subespacios topológicos"
            }
          }
        ],
        "currentTab": 1
      },
      {
        "id": "f00bee8b6c516bee",
        "type": "tabs",
        "children": [
          {
            "id": "48aeaaedf2f848b1",
            "type": "leaf",
            "state": {
              "type": "markdown",
              "state": {
                "file": "2o Mates/201 Topología/Subespacios topológicos.md",
                "mode": "source",
                "backlinks": false,
                "source": false
              },
              "icon": "lucide-file",
              "title": "Subespacios topológicos"
            }
          }
        ]
      }
    ],
    "direction": "vertical"
  },
  "left": {
    "id": "4020f4441850f88f",
    "type": "split",
    "children": [
      {
        "id": "03497693cc61b623",
        "type": "tabs",
        "children": [
          {
            "id": "5e6eb8f7956acf1a",
            "type": "leaf",
            "state": {
              "type": "file-explorer",
              "state": {
                "sortOrder": "alphabetical"
              },
              "icon": "lucide-folder-closed",
              "title": "Files"
            }
          },
          {
            "id": "6eaba0e4016b7b10",
            "type": "leaf",
            "state": {
              "type": "search",
              "state": {
                "query": "",
                "matchingCase": false,
                "explainSearch": false,
                "collapseAll": false,
                "extraContext": false,
                "sortOrder": "alphabetical"
              },
              "icon": "lucide-search",
              "title": "Search"
            }
          },
          {
            "id": "33fcadb1450c6d54",
            "type": "leaf",
            "state": {
              "type": "bookmarks",
              "state": {},
              "icon": "lucide-bookmark",
              "title": "Bookmarks"
            }
          }
        ]
      }
    ],
    "direction": "horizontal",
    "width": 200,
    "collapsed": true
  },
  "right": {
    "id": "52fd0ab846742ad2",
    "type": "split",
    "children": [
      {
        "id": "a1bb4fccfb7dfc83",
        "type": "tabs",
        "dimension": 19.93337034980566,
        "children": [
          {
            "id": "e471fcb64a8ed389",
            "type": "leaf",
            "state": {
              "type": "backlink",
              "state": {
                "collapseAll": false,
                "extraContext": true,
                "sortOrder": "alphabetical",
                "showSearch": true,
                "searchQuery": "",
                "backlinkCollapsed": false,
                "unlinkedCollapsed": true
              },
              "icon": "links-coming-in",
              "title": "Backlinks"
            }
          },
          {
            "id": "a1430b88ac7dc68e",
            "type": "leaf",
            "state": {
              "type": "tag",
              "state": {
                "sortOrder": "frequency",
                "useHierarchy": true
              },
              "icon": "lucide-tags",
              "title": "Etiquetas"
            }
          },
          {
            "id": "2f8d92bfe6fea9fd",
            "type": "leaf",
            "state": {
              "type": "outline",
              "state": {
                "file": "Teorema del grupo alternado.md"
              },
              "icon": "lucide-list",
              "title": "Esquema de Teorema del grupo alternado"
            }
          },
          {
            "id": "b6130506a792a920",
            "type": "leaf",
            "state": {
              "type": "all-properties",
              "state": {
                "sortOrder": "frequency",
                "showSearch": false,
                "searchQuery": ""
              },
              "icon": "lucide-archive",
              "title": "Todas las propiedades"
            }
          },
          {
            "id": "3c10ab461a8d3887",
            "type": "leaf",
            "state": {
              "type": "graph",
              "state": {},
              "icon": "lucide-git-fork",
              "title": "Vista gráfica"
            }
          }
        ]
      },
      {
        "id": "6cfdabfe3ebd98bf",
        "type": "tabs",
        "dimension": 80.06662965019434,
        "children": [
          {
            "id": "c1ba5ef42ced8c57",
            "type": "leaf",
            "state": {
              "type": "outgoing-link",
              "state": {
                "linksCollapsed": false,
                "unlinkedCollapsed": true
              },
              "icon": "links-going-out",
              "title": "Outgoing links"
            }
          }
        ]
      }
    ],
    "direction": "horizontal",
    "width": 200,
    "collapsed": true
  },
  "left-ribbon": {
    "hiddenItems": {
      "switcher:Open quick switcher": false,
      "graph:Open graph view": false,
      "canvas:Create new canvas": false,
      "daily-notes:Open today's daily note": false,
      "templates:Insert template": false,
      "command-palette:Open command palette": false,
      "omnisearch:Omnisearch": false,
      "obsidian-to-anki-plugin:Obsidian_to_Anki - Scan Vault": false,
      "obsidian-excalidraw-plugin:Create new drawing": false
    }
  },
  "active": "af4156d29bcf8da3",
  "lastOpenFiles": [
    "Restricción de una función continua es continua.md",
    "2o Mates/201 Topología/Subespacios topológicos.md",
    "Caracterización continuidad en un punto (restricción del codominio).md",
    "Caracterización continuidad en un punto (subespacio topológico).md",
    "Aplicación inclusión es continua.md",
    "2o Mates/201 Topología/Continuidad.md",
    "2o Mates/201 Topología/Caracterización de continuidad global (antiimagen de abiertos).md",
    "2o Mates/203 Programación matemática/203 Programación matemática.md",
    "2o Mates/203 Programación matemática/Criterio de factibilidad Dual-Simplex.md",
    "2o Mates/201 Topología/201 Topología.md",
    "2o Mates/205 Estructuras Algebraicas/Teoría de grupos.md",
    "2o Mates/205 Estructuras Algebraicas/Acciones de grupos.md",
    "2o Mates/205 Estructuras Algebraicas/Teorema de Cauchy generalizado.md",
    "2o Mates/205 Estructuras Algebraicas/Los p-subgrupos de Sylow son p-subgrupos maximales.md",
    "2o Mates/205 Estructuras Algebraicas/p-grupo.md",
    "2o Mates/205 Estructuras Algebraicas/Teorema de Sylow (referencia).md",
    "2o Mates/205 Estructuras Algebraicas/Corolario teorema de Cauchy generalizado.md",
    "2o Mates/205 Estructuras Algebraicas/p-subgrupo de Sylow.md",
    "2o Mates/205 Estructuras Algebraicas/Teorema de correspondencia.md",
    "2o Mates/205 Estructuras Algebraicas/Teorema de Cauchy para grupos abelianos.md",
    "2o Mates/205 Estructuras Algebraicas/Teorema de Lagrange (cardinal de un grupo).md",
    "2o Mates/205 Estructuras Algebraicas/Acción por conjugación.md",
    "2o Mates/205 Estructuras Algebraicas/Ecuación de las clases.md",
    "README.md",
    "2o Mates/205 Estructuras Algebraicas/Acción sobre los subgrupos.md",
    "2o Mates/205 Estructuras Algebraicas/Teorema órbita-estabilizador.md",
    "Canvas/Espacios topológicos.canvas",
    "Attachements/Pasted Image 20241115164403_866.png",
    "Attachements/Pasted Image 20241115175658_239.png",
    "Untitled",
    "Attachements",
    "Canvas/Análisis II.canvas",
    "Canvas/Teoría de grupos (canvas).canvas",
    "Análisis II.canvas",
    "Teoría de grupos (canvas).canvas",
    "Attachements/Pasted Image 20240219114609_697.png",
    "Attachements/Pasted Image 20240122154438_578.png",
    "Attachements/Pasted Image 20240103111336_357.png",
    "Attachements/Pasted Image 20231223191143_949.png",
    "Attachments/Pasted image 20231203174827.png",
    "Attachments/Pasted image 20231014120505.png",
    "Attachments/Ejercicios capítulo 1 - Eccles.pdf",
    "Attachements/image_2.png",
    "Attachements/image_1.png",
    "Excalidraw",
    "2o Mates/Marcos/Hoffstein - An Introduction to Mathematical  Cryptography",
    "2o Mates/205 Estructuras Algebraicas",
    "2o Mates/204 Métodos numéricos",
    "2o Mates/203 Programación matemática",
    "2o Mates/202 Análisis II",
    "2o Mates/201 Topología",
    "100 Análisis/Prácticas Análisis/Práctica 4/Untitled.canvas"
  ]
}